[
  {
    "type": "ShortAnswersViewer",
    "data": {
      "title": "Nome completo",
      "answers": [
        "Joao Paulo",
        "Gabriel Rodolfo",
        "Roberto Carlos",
        "Janaina Alves",
        "Douglas",
        "Paulo",
        "Leonardo",
        "Evandro",
        "Erick",
        "Luiz"
      ]
    }
  },
  {
    "type": "DateSelectViewer",
    "data": {
      "title": "Data de Nascimento",
      "dates": {
      "03/2001": [13],
      "04/2001": [20],
      "05/2001": [18],
      "10/2001": [15],
      "03/2002": [5],
      "05/2005": [10],
      "06/2006": [30],
      "01/2007": [22],
      "02/2007": [2],
      "10/2008": [24]
      }
    }
  },

  {
    "type": "DateSelectViewer",
    "data": {
      "title": "Data de Nascimento da mae",
      "dates": {
        "03/2002": [5]
      }
    }
  },

  {
    "type": "DateSelectViewer",
    "data": {
      "title": "Data de Nascimento do pai",
      "dates": {
        "03/2002": [5]
      }
    }
  },

  {
    "type": "ShortAnswersViewer",
    "data": {
      "title": "Endereço",
      "answers": ["Rua Tiradentes, Número 1638"]
    }
  },
  {
    "type": "ShortAnswersViewer",
    "data": {
      "title": "Nome dos pais ou responsáveis, caso não seja maior de 18 anos",
      "answers": ["Maria Madalena"]
    }
  },
  {
   "type":"Chart",
   "data": {
    "title": "Nível de escolaridade?",
    "labels": [
      "Nenhum",
      "Ensino Fundamental incompleto",
      "Ensino Fundamental completo",
      "Ensino Médio incompleto",
      "Ensino Médio completo",
      "Ensino superior"
    ],
    "datasets": [
      {
        "label": "# of pessoas",
        "data": [1, 1, 1, 1, 2, 4]
      }
    ]
   }
  }
]