[
    {
        "id": 1,
        "title": "Sudotec",
        "items": [
            {"id": 1, "title": "Quem somos"},
            {"id": 2, "title": "Estrutura"},
            {"id": 3, "title": "Estatuto Social"},
            {"id": 4, "title": "Regimento Interno"},
            {"id": 5, "title": "Parceiros"},
            {"id": 6, "title": "Publicações"}
        ]
    },
    {
        "id": 2,
        "title": "Portal",
        "items": [
            {"id": 7, "title": "Licitações"},
            {"id": 8, "title": "Relatório de Atividades"},
            {"id": 9, "title": "Prestação de Contas"},
            {"id": 10, "title": "Documentação Exigida"}
        ]
    },
    {
        "id": 3,
        "title": "Inclusão Digital"
    },
    {
        "id": 4,
        "title": "Maker Space"
    },
    {
        "id": 5,
        "title": "Aprender e Crescer"
    },
    {
        "id": 6,
        "title": "Incubadora Tecnológica"
    },
    {
        "id": 7,
        "title": "Imprensa"
    }
]